[
  {
    "ItemInOrder": {},
    "CustomerData": {
      "UserName": "KKD",
      "inMobileNumber": "1111111111"
    },
    "OrderData": {},
    "AddOn": {},
    "CheckOutData": {},
    "pk": 1,
    "ServerInsertedTimeStamp": "2025-08-25T12:20:30.866Z"
  },
  {
    "ItemInOrder": {},
    "CustomerData": {
      "UserName": "KKD",
      "inMobileNumber": "1111111111"
    },
    "OrderData": {},
    "AddOn": {},
    "CheckOutData": {},
    "pk": 2,
    "ServerInsertedTimeStamp": "2025-08-25T12:20:30.928Z"
  },
  {
    "ItemInOrder": {},
    "CustomerData": {
      "UserName": "KKD",
      "inMobileNumber": "5555555555"
    },
    "OrderData": {},
    "AddOn": {},
    "CheckOutData": {},
    "pk": 3,
    "ServerInsertedTimeStamp": "2025-08-25T12:56:13.195Z"
  },
  {
    "ItemInOrder": {},
    "CustomerData": {
      "UserName": "KKD",
      "inMobileNumber": "1111111111"
    },
    "OrderData": {},
    "AddOn": {},
    "CheckOutData": {},
    "pk": 4,
    "ServerInsertedTimeStamp": "2025-08-25T12:59:06.829Z"
  },
  {
    "ItemInOrder": {},
    "CustomerData": {
      "UserName": "KKD",
      "inMobileNumber": "9182896380"
    },
    "OrderData": {},
    "AddOn": {},
    "CheckOutData": {},
    "pk": 5,
    "ServerInsertedTimeStamp": "2025-08-25T12:59:32.844Z"
  },
  {
    "ItemInOrder": {},
    "CustomerData": {
      "UserName": "KKD",
      "inMobileNumber": "9848163021"
    },
    "OrderData": {},
    "AddOn": {},
    "CheckOutData": {},
    "pk": 6,
    "ServerInsertedTimeStamp": "2025-08-25T13:00:23.556Z"
  },
  {
    "ItemInOrder": {},
    "CustomerData": {
      "UserName": "KKD",
      "inMobileNumber": "2122222222"
    },
    "OrderData": {},
    "AddOn": {},
    "CheckOutData": {},
    "pk": 7,
    "ServerInsertedTimeStamp": "2025-08-25T13:01:15.246Z"
  },
  {
    "ItemInOrder": {},
    "CustomerData": {
      "UserName": "kk",
      "inMobileNumber": "9988888888"
    },
    "OrderData": {},
    "AddOn": {},
    "CheckOutData": {},
    "pk": 8,
    "ServerInsertedTimeStamp": "2025-08-25T13:04:36.198Z"
  },
  {
    "ItemInOrder": {},
    "CustomerData": {
      "UserName": "KKD",
      "inMobileNumber": "1111111111"
    },
    "OrderData": {},
    "AddOn": {},
    "CheckOutData": {},
    "pk": 9,
    "ServerInsertedTimeStamp": "2025-08-25T13:04:55.406Z"
  },
  {
    "ItemInOrder": {},
    "CustomerData": {
      "UserName": "KKD",
      "inMobileNumber": "1111111111"
    },
    "OrderData": {},
    "AddOn": {},
    "CheckOutData": {},
    "pk": 10,
    "ServerInsertedTimeStamp": "2025-08-25T13:05:10.528Z"
  },
  {
    "ItemInOrder": {},
    "CustomerData": {
      "UserName": "KKD",
      "inMobileNumber": "5555555555"
    },
    "OrderData": {},
    "AddOn": {},
    "CheckOutData": {},
    "pk": 11,
    "ServerInsertedTimeStamp": "2025-08-25T13:05:35.417Z"
  },
  {
    "ItemInOrder": {},
    "CustomerData": {
      "UserName": "KKD",
      "inMobileNumber": "9182896380"
    },
    "OrderData": {},
    "AddOn": {},
    "CheckOutData": {},
    "pk": 12,
    "ServerInsertedTimeStamp": "2025-08-25T13:06:13.557Z"
  }
]